CHANGELOG.txt
LICENCE.txt
MANIFEST.in
README.md
commands.txt
run.py
setup.py
iniUts/__init__.py
iniUts-1.1.2/CHANGELOG.txt
iniUts-1.1.2/LICENCE.txt
iniUts-1.1.2/README.md
iniUts-1.1.2/commands.txt
iniUts-1.1.2/run.py
iniUts-1.1.2/setup.py
iniUts-1.1.2/iniUts/__init__.py
iniUts-1.1.2/iniUts.egg-info/SOURCES.txt
iniUts-1.1.2/iniUts.egg-info/dependency_links.txt
iniUts-1.1.2/iniUts.egg-info/top_level.txt
iniUts-1.1.2/venv/Lib/site-packages/_distutils_hack/__init__.py
iniUts-1.1.2/venv/Lib/site-packages/_distutils_hack/override.py
iniUts-1.1.2/venv/Lib/site-packages/pip/__init__.py
iniUts-1.1.2/venv/Lib/site-packages/pip/__main__.py
iniUts-1.1.2/venv/Lib/site-packages/pip/__pip-runner__.py
iniUts-1.1.2/venv/Lib/site-packages/pip-23.3.2.dist-info/AUTHORS.txt
iniUts-1.1.2/venv/Lib/site-packages/pip-23.3.2.dist-info/LICENSE.txt
iniUts-1.1.2/venv/Lib/site-packages/pip-23.3.2.dist-info/entry_points.txt
iniUts-1.1.2/venv/Lib/site-packages/pip-23.3.2.dist-info/top_level.txt
iniUts-1.1.2/venv/Lib/site-packages/pip/_internal/__init__.py
iniUts-1.1.2/venv/Lib/site-packages/pip/_internal/build_env.py
iniUts-1.1.2/venv/Lib/site-packages/pip/_internal/cache.py
iniUts-1.1.2/venv/Lib/site-packages/pip/_internal/configuration.py
iniUts-1.1.2/venv/Lib/site-packages/pip/_internal/exceptions.py
iniUts-1.1.2/venv/Lib/site-packages/pip/_internal/main.py
iniUts-1.1.2/venv/Lib/site-packages/pip/_internal/pyproject.py
iniUts-1.1.2/venv/Lib/site-packages/pip/_internal/self_outdated_check.py
iniUts-1.1.2/venv/Lib/site-packages/pip/_internal/wheel_builder.py
iniUts-1.1.2/venv/Lib/site-packages/pip/_internal/cli/__init__.py
iniUts-1.1.2/venv/Lib/site-packages/pip/_internal/cli/autocompletion.py
iniUts-1.1.2/venv/Lib/site-packages/pip/_internal/cli/base_command.py
iniUts-1.1.2/venv/Lib/site-packages/pip/_internal/cli/cmdoptions.py
iniUts-1.1.2/venv/Lib/site-packages/pip/_internal/cli/command_context.py
iniUts-1.1.2/venv/Lib/site-packages/pip/_internal/cli/main.py
iniUts-1.1.2/venv/Lib/site-packages/pip/_internal/cli/main_parser.py
iniUts-1.1.2/venv/Lib/site-packages/pip/_internal/cli/parser.py
iniUts-1.1.2/venv/Lib/site-packages/pip/_internal/cli/progress_bars.py
iniUts-1.1.2/venv/Lib/site-packages/pip/_internal/cli/req_command.py
iniUts-1.1.2/venv/Lib/site-packages/pip/_internal/cli/spinners.py
iniUts-1.1.2/venv/Lib/site-packages/pip/_internal/cli/status_codes.py
iniUts-1.1.2/venv/Lib/site-packages/setuptools-65.5.0.dist-info/entry_points.txt
iniUts-1.1.2/venv/Lib/site-packages/setuptools-65.5.0.dist-info/top_level.txt
iniUts.egg-info/PKG-INFO
iniUts.egg-info/SOURCES.txt
iniUts.egg-info/dependency_links.txt
iniUts.egg-info/top_level.txt
venv/Lib/site-packages/pip-23.3.2.dist-info/AUTHORS.txt
venv/Lib/site-packages/pip-23.3.2.dist-info/LICENSE.txt
venv/Lib/site-packages/pip-23.3.2.dist-info/entry_points.txt
venv/Lib/site-packages/pip-23.3.2.dist-info/top_level.txt
venv/Lib/site-packages/setuptools-65.5.0.dist-info/entry_points.txt
venv/Lib/site-packages/setuptools-65.5.0.dist-info/top_level.txt
